ormbg/__init__.py
ormbg/ormbg.py
ormbg/ormbg_processor.py
snapbox_api/__init__.py
snapbox_api/cli.py
snapbox_api-0.1.1.dist-info/METADATA
snapbox_api-0.1.1.dist-info/WHEEL
snapbox_api-0.1.1.dist-info/entry_points.txt
snapbox_api-0.1.1.dist-info/top_level.txt
snapbox_api-0.1.1.dist-info/RECORD
